<accounts>
    <customer name="John Doe">
        <name>John Doe</name>
        <username>johndoe123</username>
        <address>123 Main Street, Anytown, NY 12345, United States</address>
        <email>johndoe123@sampleemail.com</email>
        <password>johndoe123</password>
        <orderHistory list="order history">
            <order>
                <product>
                    <name>Black Iced Coffee</name>
                    <type>b</type>
                    <review>5.0</review>
                    <image>Black Iced Coffee.png</image>
                    <size>small</size>
                    <quantity>2</quantity>
                </product>
                <product>
                    <name>French Roast</name>
                    <type>b</type>
                    <review>4.0</review>
                    <image>sample.png</image>
                    <size>medium</size>
                    <quantity>1</quantity>
                </product>
                <product>
                    <name>Croissant</name>
                    <type>f</type>
                    <review>3.0</review>
                    <image>sample.png</image>
                    <quantity>1</quantity>
                </product>
                <product>
                    <name>Red Velvet Cupcake</name>
                    <type>f</type>
                    <review>5.0</review>
                    <image>sample.png</image>
                    <quantity>5</quantity>
                </product>
                <timeStamp>12/23/2023</timeStamp>
                <totalPrice>345.0</totalPrice>
                <status>true</status>
                <id>0</id>
            </order>
            <order>
                <product>
                    <name>Cappuccino</name>
                    <type>b</type>
                    <review>4.0</review>
                    <image>sample.png</image>
                    <size>large</size>
                    <quantity>2</quantity>
                </product>
                <timeStamp>12/29/2023</timeStamp>
                <totalPrice>45.0</totalPrice>
                <status>true</status>
                <id>1</id>
            </order>
            <order>
                <product>
                    <name>Carrot Cake</name>
                    <type>f</type>
                    <review>4.0</review>
                    <image>sample.png</image>
                    <quantity>1</quantity>
                </product>
                <timeStamp>01/05/2024</timeStamp>
                <totalPrice>55.0</totalPrice>
                <status>true</status>
                <id>2</id>
            </order>
        </orderHistory>
    </customer>
    <customer name="Ada Lovelace">
        <name>Ada Lovelace</name>
        <username>adalovelace123</username>
        <address>123 Main Street, Barangay San Antonio, Quezon City, Metro Manila, 1105</address>
        <email>adalovelace123@sampleemail.com</email>
        <password>adalovelace</password>
        <orderHistory list="order history">
            <order>
                <product>
                    <name>Espresso Roast</name>
                    <type>b</type>
                    <review>5.0</review>
                    <image>sample.png</image>
                    <size>small</size>
                    <quantity>2</quantity>
                </product>
                <product>
                    <name>French Roast</name>
                    <type>b</type>
                    <review>4.0</review>
                    <image>sample.png</image>
                    <size>medium</size>
                    <quantity>1</quantity>
                </product>
                <product>
                    <name>Croissant</name>
                    <type>f</type>
                    <review>3.0</review>
                    <image>sample.png</image>
                    <quantity>1</quantity>
                </product>
                <product>
                    <name>Red Velvet Cupcake</name>
                    <type>f</type>
                    <review>5.0</review>
                    <image>sample.png</image>
                    <quantity>5</quantity>
                </product>
                <timeStamp>12/23/2023</timeStamp>
                <totalPrice>345.0</totalPrice>
                <status>true</status>
                <id>0</id>
            </order>
            <order>
                <product>
                    <name>Cappuccino</name>
                    <type>b</type>
                    <review>4.0</review>
                    <image>sample.png</image>
                    <size>large</size>
                    <quantity>2</quantity>
                </product>
                <timeStamp>12/29/2023</timeStamp>
                <totalPrice>45.0</totalPrice>
                <status>true</status>
                <id>1</id>
            </order>
            <order>
                <product>
                    <name>Carrot Cake</name>
                    <type>f</type>
                    <review>4.0</review>
                    <image>sample.png</image>
                    <quantity>1</quantity>
                </product>
                <timeStamp>01/05/2024</timeStamp>
                <totalPrice>55.0</totalPrice>
                <status>true</status>
                <id>2</id>
            </order>
        </orderHistory>
    </customer>
</accounts>
